dpl/dpl.py
dpl/info.py
dpl/dfpm/dfpm.py
dpl/documenter/docs.py
dpl/lib/core/arguments.py
dpl/lib/core/build.py
dpl/lib/core/cli_arguments.py
dpl/lib/core/constants.py
dpl/lib/core/error.py
dpl/lib/core/extension_support.py
dpl/lib/core/info.py
dpl/lib/core/objects.py
dpl/lib/core/py_parser.py
dpl/lib/core/restricted.py
dpl/lib/core/setup.py
dpl/lib/core/state.py
dpl/lib/core/utils.py
dpl/lib/core/varproc.py
dpl/lib/dpl_helpers/func_helper.py
dpl/lib/std/array_utils.py
dpl/lib/std/file_io.py
dpl/lib/std/math.py
dpl/lib/std/strings.py
dpl/lib/std/text_io.py
dpl/lib/std/to_dict.py
dpl/lib/std/to_py.py
dpl/lib/std/typed_vars.py
dpl/lib/std/types.py
duprol-1.4.5.dist-info/METADATA
duprol-1.4.5.dist-info/WHEEL
duprol-1.4.5.dist-info/top_level.txt
duprol-1.4.5.dist-info/RECORD
