Metadata-Version: 2.2
Name: duprol
Version: 1.4.5
Summary: A dumb programming language
Author: Darren Chase Papa
Author-email: darrenchasepapa@gmail.com
Classifier: Programming Language :: Python :: 3
Classifier: License :: OSI Approved :: MIT License
Classifier: Operating System :: OS Independent
Requires-Python: >=3.10
Requires-Dist: dill
Dynamic: author
Dynamic: author-email
Dynamic: classifier
Dynamic: description-content-type
Dynamic: requires-dist
Dynamic: requires-python
Dynamic: summary
